LICENSE
MANIFEST.in
README.md
setup.py
dsn_mongo/__init__.py
dsn_mongo/connector.py
dsn_mongo_wrapper.egg-info/PKG-INFO
dsn_mongo_wrapper.egg-info/SOURCES.txt
dsn_mongo_wrapper.egg-info/dependency_links.txt
dsn_mongo_wrapper.egg-info/not-zip-safe
dsn_mongo_wrapper.egg-info/requires.txt
dsn_mongo_wrapper.egg-info/top_level.txt