Metadata-Version: 1.1
Name: dsn-mongo-wrapper
Version: 1.0.1
Summary: A simple and lightweight wrapper for pymongo
Home-page: https://github.com/desean/mongo-wrapper
Author: ['desean']
Author-email: ['desean66@outlook.com']
License: MIT
Platform: UNKNOWN
Classifier: Development Status :: 4 - Beta
Classifier: License :: OSI Approved :: MIT License
Classifier: Programming Language :: Python :: 3.6
Classifier: Intended Audience :: Developers
Classifier: Topic :: Internet :: WWW/HTTP
Classifier: Topic :: Software Development :: Libraries :: Python Modules
